Metadata-Version: 2.4
Name: phone_agent
Version: 0.1.1
Summary: AI-powered phone automation framework
Home-page: https://github.com/zai-org/Open-AutoGLM
Author: Zhipu AI
Author-email: 
Requires-Python: >=3.12
License-File: LICENSE
Requires-Dist: build>=1.4.0
Requires-Dist: openai>=2.9.0
Requires-Dist: pillow>=12.0.0
Requires-Dist: requests>=2.31.0
Dynamic: author
Dynamic: home-page
Dynamic: license-file
Dynamic: requires-python
